readme_md_docstrings.py
readme_md_docstrings-0.1.0.dist-info/LICENSE
readme_md_docstrings-0.1.0.dist-info/METADATA
readme_md_docstrings-0.1.0.dist-info/WHEEL
readme_md_docstrings-0.1.0.dist-info/top_level.txt
readme_md_docstrings-0.1.0.dist-info/RECORD
