Metadata-Version: 2.1
Name: readme-md-docstrings
Version: 0.1.0
Summary: Update README.md from Docstrings
Home-page: UNKNOWN
Author: David Belais
Author-email: david@belais.me
License: UNKNOWN
Platform: UNKNOWN
Classifier: Programming Language :: Python :: 3
Classifier: License :: OSI Approved :: MIT License
Classifier: Operating System :: OS Independent
Requires-Python: ~=3.6
Provides-Extra: dev
Requires-Dist: wheel (>=0.34.2) ; extra == 'dev'
Requires-Dist: setuptools (>=40.8.0) ; extra == 'dev'
Requires-Dist: setuptools-setup-versions (>=0.0.30) ; extra == 'dev'
Requires-Dist: pytest (>=5.3.5) ; extra == 'dev'
Requires-Dist: tox (>=3.14.3) ; extra == 'dev'
Provides-Extra: test
Requires-Dist: pytest (>=5.3.5) ; extra == 'test'
Requires-Dist: tox (>=3.14.3) ; extra == 'test'
